<?xml version="1.0" encoding="UTF-8"?>
<stores xmlns="http://www.demandware.com/xml/impex/store/2007-04-30">
    <store store-id="vertexDistCenter">
        <name>Vertex Distribution Center</name>
        <address1>9658 West Hills Ct</address1>
        <city>Kutztown</city>
        <postal-code>19530-8643</postal-code>
        <state-code>PA</state-code>
        <country-code>US</country-code>
        <store-locator-enabled-flag>false</store-locator-enabled-flag>
        <demandware-pos-enabled-flag>false</demandware-pos-enabled-flag>
        <pos-enabled-flag>false</pos-enabled-flag>
        <custom-attributes>
            <custom-attribute attribute-id="countryCodeValue">US</custom-attribute>
        </custom-attributes>
    </store>

</stores>
