<?xml version="1.0" encoding="UTF-8"?>
<pricebooks xmlns="http://www.demandware.com/xml/impex/pricebook/2006-10-31">
    <pricebook>
        <header pricebook-id="kind-snacks-snack-club-prices">
            <currency>USD</currency>
            <display-name xml:lang="x-default">KIND Snacks Snack Club Prices</display-name>
            <online-flag>true</online-flag>
            <parent>kind-snacks-list-prices</parent>
        </header>

        <price-tables>
            <price-table product-id="vbyob20">
                <amount quantity="1.0">14.00</amount>
            </price-table>

            <price-table product-id="vbyob40">
                <amount quantity="1.0">28.00</amount>
            </price-table>

        </price-tables>
    </pricebook>
</pricebooks>
